aether/__init__.py
aether/altair_patch.py
aether/altair_plot_after_binning.py
aether/altair_plot_after_binning_facade.py
aether/decorator_cache_polars.py
aether/decorator_tracer.py
aether/markdown_embed_image.py
aether/notebook_csv_display.py
aether/obsolete.py
aether/polars_aggregation.py
aether/polars_binning.py
aether/polars_cast.py
aether/polars_corr.py
aether/polars_csv_loader.py
aether/polars_head_tail.py
aether/polars_sort.py
aether/polars_table.py
aether/polars_type.py
aether/polars_varargs_ops.py
aether/streamlit.py
aether/streamlit_components.py
aether/streamlit_csv_display.py
aether/streamlit_defer.py
aether/streamlit_form.py
aether/streamlit_key_helper.py
aether/streamlit_profile.py
aether/streamlit_query_params_access.py
aether_libra-0.1.2.dist-info/licenses/LICENSE
aether_libra-0.1.2.dist-info/METADATA
aether_libra-0.1.2.dist-info/WHEEL
aether_libra-0.1.2.dist-info/top_level.txt
aether_libra-0.1.2.dist-info/RECORD
