Metadata-Version: 2.4
Name: aether-libra
Version: 0.1.2
Summary: A lightweight utility library born from chaos and aspiring to elegance.
Author-email: libra20 <45022850+libra20@users.noreply.github.com>
License: MIT License
Project-URL: Homepage, https://github.com/libra20/aether
License-File: LICENSE
Dynamic: license-file
